Metadata-Version: 1.1
Name: inouk.recipe.odoo-cmd
Version: 0.2
Summary: Add odoo.py command to odoo appserver generated by anybox.recipe.odoo.
Home-page: https://github.com/cmorisse/inouk.recipe.odoo_cmd
Author: Cyril MORISSE
Author-email: cmorisse@boxes3.net
License: MIT
Keywords: openerp odoo recipe command
Platform: UNKNOWN
Classifier: Framework :: Buildout :: Recipe
Classifier: Development Status :: 4 - Beta
Classifier: Environment :: Console
Classifier: Intended Audience :: Developers
Classifier: Topic :: Software Development
Classifier: License :: OSI Approved :: GNU Affero General Public License v3
Classifier: Programming Language :: Python
Classifier: Natural Language :: English
